README.rst
setup.py
juju_slayer/__init__.py
juju_slayer/cli.py
juju_slayer/commands.py
juju_slayer/config.py
juju_slayer/constraints.py
juju_slayer/env.py
juju_slayer/exceptions.py
juju_slayer/ops.py
juju_slayer/provider.py
juju_slayer/runner.py
juju_slayer/ssh.py
juju_slayer.egg-info/PKG-INFO
juju_slayer.egg-info/SOURCES.txt
juju_slayer.egg-info/dependency_links.txt
juju_slayer.egg-info/entry_points.txt
juju_slayer.egg-info/requires.txt
juju_slayer.egg-info/top_level.txt
juju_slayer/tests/__init__.py
juju_slayer/tests/base.py
juju_slayer/tests/test_commands.py
juju_slayer/tests/test_config.py
juju_slayer/tests/test_constraints.py
juju_slayer/tests/test_environment.py
juju_slayer/tests/test_runner.py