Metadata-Version: 1.1
Name: juju-slayer
Version: 0.1.0
Summary: Softlayer integration with juju
Home-page: https://github.com/kapilt/juju-softlayer
Author: Kapil Thangavelu
Author-email: kapil.foss@gmail.com
License: BSD
Platform: UNKNOWN
Classifier: Intended Audience :: Developers
Classifier: Programming Language :: Python
Classifier: Operating System :: OS Independent
